Workbook

Sheet Inicio
B2: KIT AUTÓNOMO ESPAÑA
B3: VERSIÓN GRATUITA · controla facturas, gastos e IVA (Modelo 303)
B5: 1 · TUS DATOS (se usan en la plantilla de factura)
B6: Nombre y apellidos / Razón social | C6: Tu Nombre Apellidos
B7: NIF / DNI | C7: 00000000X
B8: Dirección fiscal | C8: Calle Ejemplo 1, 28001 Madrid
B9: Email / Teléfono | C9: tucorreo@email.com · 600 000 000
B10: Ejercicio (año) | C10: 2026
B12: 2 · PREFERENCIAS FISCALES
B13: Tipo de IVA habitual (%) | C13: 21 | D13: 21 general · 10 reducido · 4 superreducido · 0 exento
B14: Tipo de retención IRPF en factura (%) | C14: 15 | D14: 15 general · 7 nuevos autónomos (año alta + 2 siguientes)
B15: % de tu facturación con retención | C15: 100 | D15: Si ≥ 70% lleva retención, estás EXENTO de Modelo 130
B18: 3 · CÓMO USAR EL KIT
B19: ① Rellena tus datos y preferencias arriba.
B20: ② Apunta cada factura emitida en la pestaña «Facturas».
B21: ③ Apunta cada gasto deducible en la pestaña «Gastos».
B22: ④ Mira «Resumen trimestral»: te dice qué pagar en el Modelo 303 (IVA) y 130 (IRPF).
B23: ⑤ Usa «Plantilla factura» para emitir facturas con tus datos ya cargados.
B25: Las columnas en gris se calculan solas. No las toques: escribe solo en las blancas.
B27: AVISO: Esta hoja es una herramienta de organización, NO asesoramiento fiscal. Los tipos y reglas pueden cambiar y existen casos particulares (recargo de equivalencia, operaciones intracomunitarias, módulos, etc.). Verifica siempre con tu asesor o con la Agencia Tributaria antes de presentar cualquier modelo.
B40: 👉 Versión completa (Modelo 130 + resumen anual + Guía PDF): https://TU-ENLACE-DE-VENTA

Sheet Facturas
A1: FACTURAS EMITIDAS · ingresos
A2: Fecha | B2: Nº Factura | C2: Cliente | D2: NIF cliente | E2: Base imponible | F2: IVA % | G2: Cuota IVA | H2: IRPF % | I2: Retención IRPF | J2: Total factura | K2: ¿Cobrada? | L2: Trim.
A3: 46037 | B3: 2026-001 | C3: Cliente Ejemplo S.L. | D3: B12345678 | E3: 1000 | F3: 21 | G3: =IF($E3="","",$E3*$F3/100) | H3: 15 | I3: =IF($E3="","",$E3*$H3/100) | J3: =IF($E3="","",$E3+$G3-$I3) | K3: Sí | L3: =IF($A3="","",ROUNDUP(MONTH($A3)/3,0))
A4: 46056 | B4: 2026-002 | C4: Autónomo Pérez | D4: 12345678Z | E4: 450 | F4: 21 | G4: =IF($E4="","",$E4*$F4/100) | H4: 15 | I4: =IF($E4="","",$E4*$H4/100) | J4: =IF($E4="","",$E4+$G4-$I4) | K4: No | L4: =IF($A4="","",ROUNDUP(MONTH($A4)/3,0))
G5: =IF($E5="","",$E5*$F5/100) | I5: =IF($E5="","",$E5*$H5/100) | J5: =IF($E5="","",$E5+$G5-$I5) | L5: =IF($A5="","",ROUNDUP(MONTH($A5)/3,0))
G6: =IF($E6="","",$E6*$F6/100) | I6: =IF($E6="","",$E6*$H6/100) | J6: =IF($E6="","",$E6+$G6-$I6) | L6: =IF($A6="","",ROUNDUP(MONTH($A6)/3,0))
G7: =IF($E7="","",$E7*$F7/100) | I7: =IF($E7="","",$E7*$H7/100) | J7: =IF($E7="","",$E7+$G7-$I7) | L7: =IF($A7="","",ROUNDUP(MONTH($A7)/3,0))
G8: =IF($E8="","",$E8*$F8/100) | I8: =IF($E8="","",$E8*$H8/100) | J8: =IF($E8="","",$E8+$G8-$I8) | L8: =IF($A8="","",ROUNDUP(MONTH($A8)/3,0))
G9: =IF($E9="","",$E9*$F9/100) | I9: =IF($E9="","",$E9*$H9/100) | J9: =IF($E9="","",$E9+$G9-$I9) | L9: =IF($A9="","",ROUNDUP(MONTH($A9)/3,0))
G10: =IF($E10="","",$E10*$F10/100) | I10: =IF($E10="","",$E10*$H10/100) | J10: =IF($E10="","",$E10+$G10-$I10) | L10: =IF($A10="","",ROUNDUP(MONTH($A10)/3,0))
G11: =IF($E11="","",$E11*$F11/100) | I11: =IF($E11="","",$E11*$H11/100) | J11: =IF($E11="","",$E11+$G11-$I11) | L11: =IF($A11="","",ROUNDUP(MONTH($A11)/3,0))
G12: =IF($E12="","",$E12*$F12/100) | I12: =IF($E12="","",$E12*$H12/100) | J12: =IF($E12="","",$E12+$G12-$I12) | L12: =IF($A12="","",ROUNDUP(MONTH($A12)/3,0))
G13: =IF($E13="","",$E13*$F13/100) | I13: =IF($E13="","",$E13*$H13/100) | J13: =IF($E13="","",$E13+$G13-$I13) | L13: =IF($A13="","",ROUNDUP(MONTH($A13)/3,0))
G14: =IF($E14="","",$E14*$F14/100) | I14: =IF($E14="","",$E14*$H14/100) | J14: =IF($E14="","",$E14+$G14-$I14) | L14: =IF($A14="","",ROUNDUP(MONTH($A14)/3,0))
G15: =IF($E15="","",$E15*$F15/100) | I15: =IF($E15="","",$E15*$H15/100) | J15: =IF($E15="","",$E15+$G15-$I15) | L15: =IF($A15="","",ROUNDUP(MONTH($A15)/3,0))
G16: =IF($E16="","",$E16*$F16/100) | I16: =IF($E16="","",$E16*$H16/100) | J16: =IF($E16="","",$E16+$G16-$I16) | L16: =IF($A16="","",ROUNDUP(MONTH($A16)/3,0))
... G1000: =IF($E1000="","",$E1000*$F1000/100) | I1000: =IF($E1000="","",$E1000*$H1000/100) | J1000: =IF($E1000="","",$E1000+$G1000-$I1000) | L1000: =IF($A1000="","",ROUNDUP(MONTH($A1000)/3,0))

Sheet Gastos
A1: GASTOS DEDUCIBLES
A2: Fecha | B2: Proveedor | C2: NIF | D2: Concepto | E2: Categoría | F2: Base imponible | G2: IVA % | H2: Cuota IVA | I2: % deduc. IVA | J2: IVA deducible | K2: % deduc. IRPF | L2: Gasto deducible | M2: Trim.
A3: 46032 | B3: Movistar | C3: A82018474 | D3: Internet y móvil | E3: Suministros (luz/agua/internet) | F3: 50 | G3: 21 | H3: =IF($F3="","",$F3*$G3/100) | I3: 100 | J3: =IF($F3="","",$H3*$I3/100) | K3: 100 | L3: =IF($F3="","",$F3*$K3/100) | M3: =IF($A3="","",ROUNDUP(MONTH($A3)/3,0))
A4: 46053 | B4: Tesorería SS | D4: Cuota RETA | E4: Cuota autónomos (RETA) | F4: 80 | G4: 0 | H4: =IF($F4="","",$F4*$G4/100) | I4: 0 | J4: =IF($F4="","",$H4*$I4/100) | K4: 100 | L4: =IF($F4="","",$F4*$K4/100) | M4: =IF($A4="","",ROUNDUP(MONTH($A4)/3,0))
H5: =IF($F5="","",$F5*$G5/100) | J5: =IF($F5="","",$H5*$I5/100) | L5: =IF($F5="","",$F5*$K5/100) | M5: =IF($A5="","",ROUNDUP(MONTH($A5)/3,0))
H6: =IF($F6="","",$F6*$G6/100) | J6: =IF($F6="","",$H6*$I6/100) | L6: =IF($F6="","",$F6*$K6/100) | M6: =IF($A6="","",ROUNDUP(MONTH($A6)/3,0))
H7: =IF($F7="","",$F7*$G7/100) | J7: =IF($F7="","",$H7*$I7/100) | L7: =IF($F7="","",$F7*$K7/100) | M7: =IF($A7="","",ROUNDUP(MONTH($A7)/3,0))
H8: =IF($F8="","",$F8*$G8/100) | J8: =IF($F8="","",$H8*$I8/100) | L8: =IF($F8="","",$F8*$K8/100) | M8: =IF($A8="","",ROUNDUP(MONTH($A8)/3,0))
H9: =IF($F9="","",$F9*$G9/100) | J9: =IF($F9="","",$H9*$I9/100) | L9: =IF($F9="","",$F9*$K9/100) | M9: =IF($A9="","",ROUNDUP(MONTH($A9)/3,0))
H10: =IF($F10="","",$F10*$G10/100) | J10: =IF($F10="","",$H10*$I10/100) | L10: =IF($F10="","",$F10*$K10/100) | M10: =IF($A10="","",ROUNDUP(MONTH($A10)/3,0))
H11: =IF($F11="","",$F11*$G11/100) | J11: =IF($F11="","",$H11*$I11/100) | L11: =IF($F11="","",$F11*$K11/100) | M11: =IF($A11="","",ROUNDUP(MONTH($A11)/3,0))
H12: =IF($F12="","",$F12*$G12/100) | J12: =IF($F12="","",$H12*$I12/100) | L12: =IF($F12="","",$F12*$K12/100) | M12: =IF($A12="","",ROUNDUP(MONTH($A12)/3,0))
H13: =IF($F13="","",$F13*$G13/100) | J13: =IF($F13="","",$H13*$I13/100) | L13: =IF($F13="","",$F13*$K13/100) | M13: =IF($A13="","",ROUNDUP(MONTH($A13)/3,0))
H14: =IF($F14="","",$F14*$G14/100) | J14: =IF($F14="","",$H14*$I14/100) | L14: =IF($F14="","",$F14*$K14/100) | M14: =IF($A14="","",ROUNDUP(MONTH($A14)/3,0))
H15: =IF($F15="","",$F15*$G15/100) | J15: =IF($F15="","",$H15*$I15/100) | L15: =IF($F15="","",$F15*$K15/100) | M15: =IF($A15="","",ROUNDUP(MONTH($A15)/3,0))
H16: =IF($F16="","",$F16*$G16/100) | J16: =IF($F16="","",$H16*$I16/100) | L16: =IF($F16="","",$F16*$K16/100) | M16: =IF($A16="","",ROUNDUP(MONTH($A16)/3,0))
... H1000: =IF($F1000="","",$F1000*$G1000/100) | J1000: =IF($F1000="","",$H1000*$I1000/100) | L1000: =IF($F1000="","",$F1000*$K1000/100) | M1000: =IF($A1000="","",ROUNDUP(MONTH($A1000)/3,0))

Sheet Resumen trimestral
A1: RESUMEN TRIMESTRAL · IVA (Modelo 303)
A2: Trimestre | B2: IVA repercutido | C2: IVA soportado deducible | D2: MODELO 303 (a ingresar)
A3: T1 | B3: =SUMIFS(Facturas!$G$3:$G$1000,Facturas!$L$3:$L$1000,1) | C3: =SUMIFS(Gastos!$J$3:$J$1000,Gastos!$M$3:$M$1000,1) | D3: =B3-C3
A4: T2 | B4: =SUMIFS(Facturas!$G$3:$G$1000,Facturas!$L$3:$L$1000,2) | C4: =SUMIFS(Gastos!$J$3:$J$1000,Gastos!$M$3:$M$1000,2) | D4: =B4-C4
A5: T3 | B5: =SUMIFS(Facturas!$G$3:$G$1000,Facturas!$L$3:$L$1000,3) | C5: =SUMIFS(Gastos!$J$3:$J$1000,Gastos!$M$3:$M$1000,3) | D5: =B5-C5
A6: T4 | B6: =SUMIFS(Facturas!$G$3:$G$1000,Facturas!$L$3:$L$1000,4) | C6: =SUMIFS(Gastos!$J$3:$J$1000,Gastos!$M$3:$M$1000,4) | D6: =B6-C6
A7: AÑO | B7: =SUM(B3:B6) | C7: =SUM(C3:C6) | D7: =SUM(D3:D6)
A9: 🔒 VERSIÓN GRATUITA El cálculo AUTOMÁTICO del Modelo 130 (IRPF), el resumen anual y la Guía PDF del autónomo están en la versión completa. Consíguela aquí: https://TU-ENLACE-DE-VENTA

Sheet Plantilla factura
B2: FACTURA | E2: Nº factura: | F2: 2026-000
E3: Fecha: | F3: 2026-01-01
B4: EMISOR | E4: CLIENTE
B5: =Inicio!C6 | E5: Nombre del cliente
B6: =Inicio!C7 | E6: NIF del cliente
B7: =Inicio!C8 | E7: Dirección del cliente
B8: =Inicio!C9
B10: Concepto | D10: Cantidad | E10: Precio | F10: Importe
B11: Servicio de ejemplo | D11: 1 | E11: 1000 | F11: =IF(D11="","",D11*E11)
F12: =IF(D12="","",D12*E12)
F13: =IF(D13="","",D13*E13)
F14: =IF(D14="","",D14*E14)
F15: =IF(D15="","",D15*E15)
E17: Base imponible | F17: =SUM(F11:F16)
E18: IVA | F18: =F17*Inicio!$C$11/100
E19: Retención IRPF | F19: =-F17*Inicio!$C$12/100
E20: TOTAL | F20: =F17+F18+F19
B22: Factura exenta de IVA: art. 20 LIVA (elimina la fila de IVA si aplica). Conserva copia de todas tus facturas emitidas y recibidas durante 4 años.

Sheet Listas
A1: IVA | B1: IRPF | C1: SiNo | D1: Categorias
A2: 21 | B2: 15 | C2: Sí | D2: Suministros (luz/agua/internet)
A3: 10 | B3: 7 | C3: No | D3: Material y software
A4: 4 | B4: 1 | D4: Cuota autónomos (RETA)
A5: 0 | B5: 0 | D5: Asesoría / gestoría
D6: Marketing y publicidad
D7: Desplazamientos
D8: Formación
D9: Alquiler oficina/coworking
D10: Telefonía
D11: Comisiones bancarias
D12: Otros
